observable_variable/__init__.py
observable_variable/main.py
observable_variable-0.0.2.dist-info/licenses/LICENSE
observable_variable-0.0.2.dist-info/METADATA
observable_variable-0.0.2.dist-info/WHEEL
observable_variable-0.0.2.dist-info/top_level.txt
observable_variable-0.0.2.dist-info/RECORD
